{
  "leadership": {
    "members": [
      "yh4"
    ],
    "admins": [
      "yh4"
    ]
  },
  "teams": {
    "cmuresearch": {
      "members": [],
      "admins": []
    },
    "cmuservice": {
      "members": [
        "benliu"
      ],
      "admins": [
        "benliu"
      ]
    },
    "collegecart": {
      "members": [
        "rushabhj"
      ],
      "admins": [
        "rushabhj"
      ],
      "website": "https://collegecart.org",
      "server": "https://api.collegecart.org"
    }
  }
}
